huey_django_orm/__init__.py
huey_django_orm/admin.py
huey_django_orm/apps.py
huey_django_orm/models.py
huey_django_orm/storage.py
huey_django_orm/tests.py
huey_django_orm/views.py
huey_django_orm/migrations/0001_initial.py
huey_django_orm/migrations/__init__.py
huey_django_orm-24.10.24.0.dist-info/LICENSE
huey_django_orm-24.10.24.0.dist-info/METADATA
huey_django_orm-24.10.24.0.dist-info/WHEEL
huey_django_orm-24.10.24.0.dist-info/top_level.txt
huey_django_orm-24.10.24.0.dist-info/RECORD
