Metadata-Version: 2.1
Name: huey_django_orm
Version: 24.10.24.0
Summary: A module to use Django ORM for storage with huey.
Home-page: https://github.com/avryhof/huey_django_orm
Author: Amos Vryhof
Author-email: avryhof@gmail.com
License: MIT
Project-URL: GitHub Repo, https://github.com/avryhof/huey_django_orm
Project-URL: Bug Tracker, https://github.com/avryhof/huey_django_orm/issues
Keywords: huey,django,huey.contrib.djhuey
Classifier: Development Status :: 5 - Production/Stable
Classifier: Framework :: Django
Classifier: Intended Audience :: Developers
Classifier: License :: OSI Approved :: MIT License
Classifier: Natural Language :: English
Classifier: Programming Language :: Python :: 3.7
Classifier: Programming Language :: Python :: 3.8
Classifier: Programming Language :: Python :: 3.9
Classifier: Programming Language :: Python :: 3.10
License-File: LICENSE
Requires-Dist: Django
Requires-Dist: huey
